banshee/__init__.py
banshee/builder.py
banshee/bus.py
banshee/context.py
banshee/errors.py
banshee/extra/__init__.py
banshee/extra/injector.py
banshee/message.py
banshee/middleware/__init__.py
banshee/middleware/causation.py
banshee/middleware/dispatch.py
banshee/middleware/gate.py
banshee/middleware/handle_after.py
banshee/middleware/identity.py
banshee/py.typed
banshee/registry.py
banshee/request.py
banshee/testing.py
banshee-0.1.1.dist-info/METADATA
banshee-0.1.1.dist-info/WHEEL
banshee-0.1.1.dist-info/RECORD
