Metadata-Version: 2.1
Name: banshee
Version: 0.1.1
Summary: 
Author: Your Name
Author-email: you@example.com
Requires-Python: >=3.10,<4.0
Classifier: Programming Language :: Python :: 3
Classifier: Programming Language :: Python :: 3.10
Classifier: Programming Language :: Python :: 3.11
Classifier: Programming Language :: Python :: 3.12
Provides-Extra: injector
Requires-Dist: exceptiongroup (>=1.0.0-rc.3,<2.0.0)
Requires-Dist: injector (>=0.19,<0.22) ; extra == "injector"
